egglib/__init__.py
egglib/_eggwrapper.cpython-38-darwin.so
egglib/_freq.py
egglib/_interface.py
egglib/_site.py
egglib/_tree.py
egglib/alphabets.py
egglib/eggwrapper.py
egglib/random.py
egglib/coalesce/__init__.py
egglib/coalesce/_param_helpers.py
egglib/coalesce/_simulator.py
egglib/io/__init__.py
egglib/io/_fasta.py
egglib/io/_genbank.py
egglib/io/_genepop.py
egglib/io/_gff3.py
egglib/io/_legacy.py
egglib/io/_ms.py
egglib/io/_vcf.py
egglib/stats/__init__.py
egglib/stats/_baudry.py
egglib/stats/_coding_diversity.py
egglib/stats/_cstats.py
egglib/stats/_ehh.py
egglib/stats/_haplotypes.py
egglib/stats/_ld.py
egglib/stats/_paralog_pi.py
egglib/tools/__init__.py
egglib/tools/_code_tools.py
egglib/tools/_concat.py
egglib/tools/_reading_frame.py
egglib/tools/_seq_manip.py
egglib/tools/_to_codons.py
egglib/wrappers/__init__.py
egglib/wrappers/_blast.py
egglib/wrappers/_clustal.py
egglib/wrappers/_codeml.py
egglib/wrappers/_muscle.py
egglib/wrappers/_nj.py
egglib/wrappers/_phyml.py
egglib/wrappers/_utils.py
EggLib-3.1.0.dist-info/COPYING
EggLib-3.1.0.dist-info/LICENSE
EggLib-3.1.0.dist-info/METADATA
EggLib-3.1.0.dist-info/WHEEL
EggLib-3.1.0.dist-info/top_level.txt
EggLib-3.1.0.dist-info/RECORD
