Metadata-Version: 2.1
Name: EggLib
Version: 3.1.0
Summary: Evolutionary Genetics and Genomics Library
Home-page: https://egglib.org/
Author: Stéphane De Mita, Mathieu Siol
Author-email: demita@gmail.com
License: GPL v3
Download-URL: https://pypi.org/project/EggLib/3.1.0/#files
Project-URL: Bug Tracker, https://gitlab.com/demita/egglib/-/issues
Project-URL: Documentation, https://egglib.org/
Project-URL: Source Code, https://gitlab.com/demita/egglib/-/tree/master
Platform: platform-independent
Classifier: Programming Language :: Python :: 3.6
Classifier: Programming Language :: Python :: 3.7
Classifier: Programming Language :: Python :: 3.8
Classifier: Programming Language :: Python :: 3.9
Classifier: License :: OSI Approved :: GNU General Public License v3 or later (GPLv3+)
Classifier: Operating System :: OS Independent
Provides-Extra: doc
Requires-Dist: numpydoc ; extra == 'doc'
